wink_sdk_extranet_distribution/__init__.py
wink_sdk_extranet_distribution/api_client.py
wink_sdk_extranet_distribution/api_response.py
wink_sdk_extranet_distribution/configuration.py
wink_sdk_extranet_distribution/exceptions.py
wink_sdk_extranet_distribution/py.typed
wink_sdk_extranet_distribution/rest.py
wink_sdk_extranet_distribution/api/__init__.py
wink_sdk_extranet_distribution/api/affiliate_api.py
wink_sdk_extranet_distribution/api/daily_rate_api.py
wink_sdk_extranet_distribution/api/inventory_api.py
wink_sdk_extranet_distribution/api/inventory_usage_api.py
wink_sdk_extranet_distribution/api/sales_channel_api.py
wink_sdk_extranet_distribution/api/sales_channel_relationship_requests_api.py
wink_sdk_extranet_distribution/api/sales_channel_request_api.py
wink_sdk_extranet_distribution/api/scheduler_api.py
wink_sdk_extranet_distribution/models/__init__.py
wink_sdk_extranet_distribution/models/add_on_lightweight_supplier_details.py
wink_sdk_extranet_distribution/models/add_on_localized_inventory_supplier_details.py
wink_sdk_extranet_distribution/models/add_on_supplier_details.py
wink_sdk_extranet_distribution/models/address_supplier.py
wink_sdk_extranet_distribution/models/address_supplier_details.py
wink_sdk_extranet_distribution/models/advance_booking_rate_qualifier_supplier.py
wink_sdk_extranet_distribution/models/advance_booking_rate_qualifier_supplier_details.py
wink_sdk_extranet_distribution/models/aggregate_descriptor_supplier.py
wink_sdk_extranet_distribution/models/arrival_days_of_week_rate_qualifier_supplier.py
wink_sdk_extranet_distribution/models/arrival_days_of_week_rate_qualifier_supplier_details.py
wink_sdk_extranet_distribution/models/authenticated_user_supplier_details.py
wink_sdk_extranet_distribution/models/available_days_of_week_rate_qualifier_supplier.py
wink_sdk_extranet_distribution/models/available_days_of_week_rate_qualifier_supplier_details.py
wink_sdk_extranet_distribution/models/bed_supplier_details.py
wink_sdk_extranet_distribution-0.0.57.dist-info/licenses/LICENSE
wink_sdk_extranet_distribution-0.0.57.dist-info/METADATA
wink_sdk_extranet_distribution-0.0.57.dist-info/WHEEL
wink_sdk_extranet_distribution-0.0.57.dist-info/top_level.txt
wink_sdk_extranet_distribution-0.0.57.dist-info/RECORD
